<?xml version="1.0" ?>
<annotation>
 <folder>Cityscapes</folder>
 <filename>source_bremen_000041_000019_leftImg8bit.jpg</filename>
 <source>
  <database>Cityscapes</database>
  <annotation>PASCAL VOC2007</annotation>
 </source>
 <size>
  <width>2048</width>
  <height>1024</height>
  <depth>3</depth>
 </size>
 <segmented>0</segmented>
 <object>
  <name>person</name>
  <truncated>0</truncated>
  <difficult>0</difficult>
  <bndbox>
   <xmin>770</xmin>
   <ymin>415</ymin>
   <xmax>781</xmax>
   <ymax>468</ymax>
  </bndbox>
 </object>
 <object>
  <name>car</name>
  <truncated>0</truncated>
  <difficult>0</difficult>
  <bndbox>
   <xmin>446</xmin>
   <ymin>374</ymin>
   <xmax>721</xmax>
   <ymax>541</ymax>
  </bndbox>
 </object>
 <object>
  <name>bicycle</name>
  <truncated>0</truncated>
  <difficult>0</difficult>
  <bndbox>
   <xmin>1211</xmin>
   <ymin>413</ymin>
   <xmax>1297</xmax>
   <ymax>574</ymax>
  </bndbox>
 </object>
 <object>
  <name>bicycle</name>
  <truncated>0</truncated>
  <difficult>0</difficult>
  <bndbox>
   <xmin>989</xmin>
   <ymin>430</ymin>
   <xmax>1020</xmax>
   <ymax>436</ymax>
  </bndbox>
 </object>
</annotation>
