<?xml version="1.0" ?>
<annotation>
 <folder>Cityscapes</folder>
 <filename>source_bremen_000175_000019_leftImg8bit.jpg</filename>
 <source>
  <database>Cityscapes</database>
  <annotation>PASCAL VOC2007</annotation>
 </source>
 <size>
  <width>2048</width>
  <height>1024</height>
  <depth>3</depth>
 </size>
 <segmented>0</segmented>
 <object>
  <name>person</name>
  <truncated>0</truncated>
  <difficult>0</difficult>
  <bndbox>
   <xmin>250</xmin>
   <ymin>419</ymin>
   <xmax>1147</xmax>
   <ymax>496</ymax>
  </bndbox>
 </object>
 <object>
  <name>person</name>
  <truncated>0</truncated>
  <difficult>0</difficult>
  <bndbox>
   <xmin>984</xmin>
   <ymin>428</ymin>
   <xmax>995</xmax>
   <ymax>474</ymax>
  </bndbox>
 </object>
 <object>
  <name>person</name>
  <truncated>0</truncated>
  <difficult>0</difficult>
  <bndbox>
   <xmin>1332</xmin>
   <ymin>415</ymin>
   <xmax>1351</xmax>
   <ymax>479</ymax>
  </bndbox>
 </object>
 <object>
  <name>person</name>
  <truncated>0</truncated>
  <difficult>0</difficult>
  <bndbox>
   <xmin>1235</xmin>
   <ymin>415</ymin>
   <xmax>1243</xmax>
   <ymax>425</ymax>
  </bndbox>
 </object>
 <object>
  <name>person</name>
  <truncated>0</truncated>
  <difficult>0</difficult>
  <bndbox>
   <xmin>1234</xmin>
   <ymin>423</ymin>
   <xmax>1260</xmax>
   <ymax>499</ymax>
  </bndbox>
 </object>
 <object>
  <name>car</name>
  <truncated>0</truncated>
  <difficult>0</difficult>
  <bndbox>
   <xmin>27</xmin>
   <ymin>438</ymin>
   <xmax>239</xmax>
   <ymax>539</ymax>
  </bndbox>
 </object>
 <object>
  <name>car</name>
  <truncated>0</truncated>
  <difficult>0</difficult>
  <bndbox>
   <xmin>871</xmin>
   <ymin>443</ymin>
   <xmax>897</xmax>
   <ymax>466</ymax>
  </bndbox>
 </object>
 <object>
  <name>car</name>
  <truncated>0</truncated>
  <difficult>0</difficult>
  <bndbox>
   <xmin>840</xmin>
   <ymin>444</ymin>
   <xmax>878</xmax>
   <ymax>468</ymax>
  </bndbox>
 </object>
 <object>
  <name>car</name>
  <truncated>0</truncated>
  <difficult>0</difficult>
  <bndbox>
   <xmin>781</xmin>
   <ymin>439</ymin>
   <xmax>828</xmax>
   <ymax>474</ymax>
  </bndbox>
 </object>
 <object>
  <name>car</name>
  <truncated>0</truncated>
  <difficult>0</difficult>
  <bndbox>
   <xmin>747</xmin>
   <ymin>445</ymin>
   <xmax>780</xmax>
   <ymax>476</ymax>
  </bndbox>
 </object>
 <object>
  <name>car</name>
  <truncated>0</truncated>
  <difficult>0</difficult>
  <bndbox>
   <xmin>733</xmin>
   <ymin>446</ymin>
   <xmax>762</xmax>
   <ymax>478</ymax>
  </bndbox>
 </object>
 <object>
  <name>car</name>
  <truncated>0</truncated>
  <difficult>0</difficult>
  <bndbox>
   <xmin>699</xmin>
   <ymin>440</ymin>
   <xmax>742</xmax>
   <ymax>487</ymax>
  </bndbox>
 </object>
 <object>
  <name>car</name>
  <truncated>0</truncated>
  <difficult>0</difficult>
  <bndbox>
   <xmin>654</xmin>
   <ymin>438</ymin>
   <xmax>711</xmax>
   <ymax>488</ymax>
  </bndbox>
 </object>
 <object>
  <name>car</name>
  <truncated>0</truncated>
  <difficult>0</difficult>
  <bndbox>
   <xmin>537</xmin>
   <ymin>446</ymin>
   <xmax>598</xmax>
   <ymax>496</ymax>
  </bndbox>
 </object>
 <object>
  <name>car</name>
  <truncated>0</truncated>
  <difficult>0</difficult>
  <bndbox>
   <xmin>580</xmin>
   <ymin>440</ymin>
   <xmax>668</xmax>
   <ymax>498</ymax>
  </bndbox>
 </object>
 <object>
  <name>car</name>
  <truncated>0</truncated>
  <difficult>0</difficult>
  <bndbox>
   <xmin>426</xmin>
   <ymin>440</ymin>
   <xmax>522</xmax>
   <ymax>507</ymax>
  </bndbox>
 </object>
 <object>
  <name>car</name>
  <truncated>0</truncated>
  <difficult>0</difficult>
  <bndbox>
   <xmin>1017</xmin>
   <ymin>426</ymin>
   <xmax>1045</xmax>
   <ymax>449</ymax>
  </bndbox>
 </object>
 <object>
  <name>car</name>
  <truncated>0</truncated>
  <difficult>0</difficult>
  <bndbox>
   <xmin>1016</xmin>
   <ymin>442</ymin>
   <xmax>1038</xmax>
   <ymax>466</ymax>
  </bndbox>
 </object>
 <object>
  <name>car</name>
  <truncated>0</truncated>
  <difficult>0</difficult>
  <bndbox>
   <xmin>1046</xmin>
   <ymin>425</ymin>
   <xmax>1073</xmax>
   <ymax>432</ymax>
  </bndbox>
 </object>
 <object>
  <name>car</name>
  <truncated>0</truncated>
  <difficult>0</difficult>
  <bndbox>
   <xmin>1033</xmin>
   <ymin>432</ymin>
   <xmax>1097</xmax>
   <ymax>487</ymax>
  </bndbox>
 </object>
 <object>
  <name>car</name>
  <truncated>0</truncated>
  <difficult>0</difficult>
  <bndbox>
   <xmin>1945</xmin>
   <ymin>420</ymin>
   <xmax>2031</xmax>
   <ymax>482</ymax>
  </bndbox>
 </object>
 <object>
  <name>car</name>
  <truncated>0</truncated>
  <difficult>0</difficult>
  <bndbox>
   <xmin>1950</xmin>
   <ymin>443</ymin>
   <xmax>2043</xmax>
   <ymax>519</ymax>
  </bndbox>
 </object>
 <object>
  <name>car</name>
  <truncated>0</truncated>
  <difficult>0</difficult>
  <bndbox>
   <xmin>2012</xmin>
   <ymin>455</ymin>
   <xmax>2043</xmax>
   <ymax>521</ymax>
  </bndbox>
 </object>
 <object>
  <name>car</name>
  <truncated>0</truncated>
  <difficult>0</difficult>
  <bndbox>
   <xmin>1654</xmin>
   <ymin>422</ymin>
   <xmax>1802</xmax>
   <ymax>494</ymax>
  </bndbox>
 </object>
 <object>
  <name>car</name>
  <truncated>0</truncated>
  <difficult>0</difficult>
  <bndbox>
   <xmin>1247</xmin>
   <ymin>415</ymin>
   <xmax>1306</xmax>
   <ymax>467</ymax>
  </bndbox>
 </object>
 <object>
  <name>car</name>
  <truncated>0</truncated>
  <difficult>0</difficult>
  <bndbox>
   <xmin>7</xmin>
   <ymin>591</ymin>
   <xmax>28</xmax>
   <ymax>928</ymax>
  </bndbox>
 </object>
 <object>
  <name>bicycle</name>
  <truncated>0</truncated>
  <difficult>0</difficult>
  <bndbox>
   <xmin>1726</xmin>
   <ymin>447</ymin>
   <xmax>1880</xmax>
   <ymax>564</ymax>
  </bndbox>
 </object>
 <object>
  <name>bicycle</name>
  <truncated>0</truncated>
  <difficult>0</difficult>
  <bndbox>
   <xmin>1553</xmin>
   <ymin>451</ymin>
   <xmax>1633</xmax>
   <ymax>585</ymax>
  </bndbox>
 </object>
 <object>
  <name>bicycle</name>
  <truncated>0</truncated>
  <difficult>0</difficult>
  <bndbox>
   <xmin>1618</xmin>
   <ymin>444</ymin>
   <xmax>1708</xmax>
   <ymax>601</ymax>
  </bndbox>
 </object>
 <object>
  <name>bicycle</name>
  <truncated>0</truncated>
  <difficult>0</difficult>
  <bndbox>
   <xmin>1682</xmin>
   <ymin>482</ymin>
   <xmax>1870</xmax>
   <ymax>628</ymax>
  </bndbox>
 </object>
 <object>
  <name>bicycle</name>
  <truncated>0</truncated>
  <difficult>0</difficult>
  <bndbox>
   <xmin>1505</xmin>
   <ymin>443</ymin>
   <xmax>1534</xmax>
   <ymax>485</ymax>
  </bndbox>
 </object>
 <object>
  <name>bicycle</name>
  <truncated>0</truncated>
  <difficult>0</difficult>
  <bndbox>
   <xmin>1236</xmin>
   <ymin>460</ymin>
   <xmax>1285</xmax>
   <ymax>495</ymax>
  </bndbox>
 </object>
</annotation>
