<?xml version="1.0" ?>
<annotation>
 <folder>Cityscapes</folder>
 <filename>source_darmstadt_000030_000019_leftImg8bit.jpg</filename>
 <source>
  <database>Cityscapes</database>
  <annotation>PASCAL VOC2007</annotation>
 </source>
 <size>
  <width>2048</width>
  <height>1024</height>
  <depth>3</depth>
 </size>
 <segmented>0</segmented>
 <object>
  <name>car</name>
  <truncated>0</truncated>
  <difficult>0</difficult>
  <bndbox>
   <xmin>868</xmin>
   <ymin>364</ymin>
   <xmax>903</xmax>
   <ymax>375</ymax>
  </bndbox>
 </object>
 <object>
  <name>person</name>
  <truncated>0</truncated>
  <difficult>0</difficult>
  <bndbox>
   <xmin>252</xmin>
   <ymin>382</ymin>
   <xmax>276</xmax>
   <ymax>401</ymax>
  </bndbox>
 </object>
 <object>
  <name>person</name>
  <truncated>0</truncated>
  <difficult>0</difficult>
  <bndbox>
   <xmin>2012</xmin>
   <ymin>369</ymin>
   <xmax>2036</xmax>
   <ymax>404</ymax>
  </bndbox>
 </object>
 <object>
  <name>person</name>
  <truncated>0</truncated>
  <difficult>0</difficult>
  <bndbox>
   <xmin>1806</xmin>
   <ymin>366</ymin>
   <xmax>1816</xmax>
   <ymax>379</ymax>
  </bndbox>
 </object>
 <object>
  <name>car</name>
  <truncated>0</truncated>
  <difficult>0</difficult>
  <bndbox>
   <xmin>1505</xmin>
   <ymin>376</ymin>
   <xmax>1532</xmax>
   <ymax>390</ymax>
  </bndbox>
 </object>
 <object>
  <name>car</name>
  <truncated>0</truncated>
  <difficult>0</difficult>
  <bndbox>
   <xmin>1506</xmin>
   <ymin>379</ymin>
   <xmax>1548</xmax>
   <ymax>411</ymax>
  </bndbox>
 </object>
 <object>
  <name>car</name>
  <truncated>0</truncated>
  <difficult>0</difficult>
  <bndbox>
   <xmin>1456</xmin>
   <ymin>381</ymin>
   <xmax>1515</xmax>
   <ymax>426</ymax>
  </bndbox>
 </object>
 <object>
  <name>car</name>
  <truncated>0</truncated>
  <difficult>0</difficult>
  <bndbox>
   <xmin>1333</xmin>
   <ymin>379</ymin>
   <xmax>1352</xmax>
   <ymax>401</ymax>
  </bndbox>
 </object>
 <object>
  <name>car</name>
  <truncated>0</truncated>
  <difficult>0</difficult>
  <bndbox>
   <xmin>1352</xmin>
   <ymin>371</ymin>
   <xmax>1412</xmax>
   <ymax>429</ymax>
  </bndbox>
 </object>
 <object>
  <name>car</name>
  <truncated>0</truncated>
  <difficult>0</difficult>
  <bndbox>
   <xmin>1400</xmin>
   <ymin>380</ymin>
   <xmax>1481</xmax>
   <ymax>440</ymax>
  </bndbox>
 </object>
 <object>
  <name>car</name>
  <truncated>0</truncated>
  <difficult>0</difficult>
  <bndbox>
   <xmin>1070</xmin>
   <ymin>293</ymin>
   <xmax>1325</xmax>
   <ymax>496</ymax>
  </bndbox>
 </object>
 <object>
  <name>car</name>
  <truncated>0</truncated>
  <difficult>0</difficult>
  <bndbox>
   <xmin>869</xmin>
   <ymin>375</ymin>
   <xmax>918</xmax>
   <ymax>388</ymax>
  </bndbox>
 </object>
 <object>
  <name>car</name>
  <truncated>0</truncated>
  <difficult>0</difficult>
  <bndbox>
   <xmin>781</xmin>
   <ymin>389</ymin>
   <xmax>1001</xmax>
   <ymax>496</ymax>
  </bndbox>
 </object>
 <object>
  <name>car</name>
  <truncated>0</truncated>
  <difficult>0</difficult>
  <bndbox>
   <xmin>7</xmin>
   <ymin>383</ymin>
   <xmax>454</xmax>
   <ymax>558</ymax>
  </bndbox>
 </object>
 <object>
  <name>car</name>
  <truncated>0</truncated>
  <difficult>0</difficult>
  <bndbox>
   <xmin>7</xmin>
   <ymin>479</ymin>
   <xmax>138</xmax>
   <ymax>939</ymax>
  </bndbox>
 </object>
 <object>
  <name>truck</name>
  <truncated>0</truncated>
  <difficult>0</difficult>
  <bndbox>
   <xmin>1951</xmin>
   <ymin>342</ymin>
   <xmax>2043</xmax>
   <ymax>404</ymax>
  </bndbox>
 </object>
 <object>
  <name>truck</name>
  <truncated>0</truncated>
  <difficult>0</difficult>
  <bndbox>
   <xmin>1420</xmin>
   <ymin>345</ymin>
   <xmax>1486</xmax>
   <ymax>385</ymax>
  </bndbox>
 </object>
 <object>
  <name>truck</name>
  <truncated>0</truncated>
  <difficult>0</difficult>
  <bndbox>
   <xmin>961</xmin>
   <ymin>352</ymin>
   <xmax>1065</xmax>
   <ymax>437</ymax>
  </bndbox>
 </object>
 <object>
  <name>truck</name>
  <truncated>0</truncated>
  <difficult>0</difficult>
  <bndbox>
   <xmin>280</xmin>
   <ymin>284</ymin>
   <xmax>706</xmax>
   <ymax>501</ymax>
  </bndbox>
 </object>
 <object>
  <name>truck</name>
  <truncated>0</truncated>
  <difficult>0</difficult>
  <bndbox>
   <xmin>1869</xmin>
   <ymin>338</ymin>
   <xmax>1952</xmax>
   <ymax>407</ymax>
  </bndbox>
 </object>
</annotation>
