<?xml version="1.0" ?>
<annotation>
 <folder>Cityscapes</folder>
 <filename>source_bremen_000259_000019_leftImg8bit.jpg</filename>
 <source>
  <database>Cityscapes</database>
  <annotation>PASCAL VOC2007</annotation>
 </source>
 <size>
  <width>2048</width>
  <height>1024</height>
  <depth>3</depth>
 </size>
 <segmented>0</segmented>
 <object>
  <name>person</name>
  <truncated>0</truncated>
  <difficult>0</difficult>
  <bndbox>
   <xmin>832</xmin>
   <ymin>427</ymin>
   <xmax>842</xmax>
   <ymax>451</ymax>
  </bndbox>
 </object>
 <object>
  <name>person</name>
  <truncated>0</truncated>
  <difficult>0</difficult>
  <bndbox>
   <xmin>846</xmin>
   <ymin>417</ymin>
   <xmax>865</xmax>
   <ymax>452</ymax>
  </bndbox>
 </object>
 <object>
  <name>car</name>
  <truncated>0</truncated>
  <difficult>0</difficult>
  <bndbox>
   <xmin>916</xmin>
   <ymin>430</ymin>
   <xmax>962</xmax>
   <ymax>461</ymax>
  </bndbox>
 </object>
 <object>
  <name>car</name>
  <truncated>0</truncated>
  <difficult>0</difficult>
  <bndbox>
   <xmin>962</xmin>
   <ymin>420</ymin>
   <xmax>998</xmax>
   <ymax>464</ymax>
  </bndbox>
 </object>
 <object>
  <name>car</name>
  <truncated>0</truncated>
  <difficult>0</difficult>
  <bndbox>
   <xmin>650</xmin>
   <ymin>426</ymin>
   <xmax>766</xmax>
   <ymax>465</ymax>
  </bndbox>
 </object>
 <object>
  <name>car</name>
  <truncated>0</truncated>
  <difficult>0</difficult>
  <bndbox>
   <xmin>591</xmin>
   <ymin>427</ymin>
   <xmax>615</xmax>
   <ymax>468</ymax>
  </bndbox>
 </object>
 <object>
  <name>car</name>
  <truncated>0</truncated>
  <difficult>0</difficult>
  <bndbox>
   <xmin>966</xmin>
   <ymin>390</ymin>
   <xmax>1137</xmax>
   <ymax>586</ymax>
  </bndbox>
 </object>
 <object>
  <name>car</name>
  <truncated>0</truncated>
  <difficult>0</difficult>
  <bndbox>
   <xmin>1445</xmin>
   <ymin>395</ymin>
   <xmax>1616</xmax>
   <ymax>505</ymax>
  </bndbox>
 </object>
 <object>
  <name>car</name>
  <truncated>0</truncated>
  <difficult>0</difficult>
  <bndbox>
   <xmin>1499</xmin>
   <ymin>414</ymin>
   <xmax>1888</xmax>
   <ymax>643</ymax>
  </bndbox>
 </object>
 <object>
  <name>car</name>
  <truncated>0</truncated>
  <difficult>0</difficult>
  <bndbox>
   <xmin>1038</xmin>
   <ymin>294</ymin>
   <xmax>1549</xmax>
   <ymax>774</ymax>
  </bndbox>
 </object>
 <object>
  <name>bus</name>
  <truncated>0</truncated>
  <difficult>0</difficult>
  <bndbox>
   <xmin>7</xmin>
   <ymin>263</ymin>
   <xmax>593</xmax>
   <ymax>585</ymax>
  </bndbox>
 </object>
</annotation>
