<?xml version="1.0" ?>
<annotation>
 <folder>Cityscapes</folder>
 <filename>source_tubingen_000111_000019_leftImg8bit.jpg</filename>
 <source>
  <database>Cityscapes</database>
  <annotation>PASCAL VOC2007</annotation>
 </source>
 <size>
  <width>2048</width>
  <height>1024</height>
  <depth>3</depth>
 </size>
 <segmented>0</segmented>
 <object>
  <name>person</name>
  <truncated>0</truncated>
  <difficult>0</difficult>
  <bndbox>
   <xmin>1118</xmin>
   <ymin>413</ymin>
   <xmax>1147</xmax>
   <ymax>491</ymax>
  </bndbox>
 </object>
 <object>
  <name>car</name>
  <truncated>0</truncated>
  <difficult>0</difficult>
  <bndbox>
   <xmin>826</xmin>
   <ymin>442</ymin>
   <xmax>866</xmax>
   <ymax>471</ymax>
  </bndbox>
 </object>
 <object>
  <name>car</name>
  <truncated>0</truncated>
  <difficult>0</difficult>
  <bndbox>
   <xmin>778</xmin>
   <ymin>440</ymin>
   <xmax>812</xmax>
   <ymax>480</ymax>
  </bndbox>
 </object>
 <object>
  <name>car</name>
  <truncated>0</truncated>
  <difficult>0</difficult>
  <bndbox>
   <xmin>723</xmin>
   <ymin>439</ymin>
   <xmax>787</xmax>
   <ymax>488</ymax>
  </bndbox>
 </object>
 <object>
  <name>car</name>
  <truncated>0</truncated>
  <difficult>0</difficult>
  <bndbox>
   <xmin>669</xmin>
   <ymin>449</ymin>
   <xmax>700</xmax>
   <ymax>501</ymax>
  </bndbox>
 </object>
 <object>
  <name>car</name>
  <truncated>0</truncated>
  <difficult>0</difficult>
  <bndbox>
   <xmin>578</xmin>
   <ymin>439</ymin>
   <xmax>676</xmax>
   <ymax>511</ymax>
  </bndbox>
 </object>
 <object>
  <name>car</name>
  <truncated>0</truncated>
  <difficult>0</difficult>
  <bndbox>
   <xmin>1087</xmin>
   <ymin>436</ymin>
   <xmax>1101</xmax>
   <ymax>462</ymax>
  </bndbox>
 </object>
 <object>
  <name>car</name>
  <truncated>0</truncated>
  <difficult>0</difficult>
  <bndbox>
   <xmin>1095</xmin>
   <ymin>432</ymin>
   <xmax>1112</xmax>
   <ymax>466</ymax>
  </bndbox>
 </object>
 <object>
  <name>car</name>
  <truncated>0</truncated>
  <difficult>0</difficult>
  <bndbox>
   <xmin>1101</xmin>
   <ymin>432</ymin>
   <xmax>1119</xmax>
   <ymax>469</ymax>
  </bndbox>
 </object>
 <object>
  <name>car</name>
  <truncated>0</truncated>
  <difficult>0</difficult>
  <bndbox>
   <xmin>1109</xmin>
   <ymin>430</ymin>
   <xmax>1147</xmax>
   <ymax>478</ymax>
  </bndbox>
 </object>
 <object>
  <name>car</name>
  <truncated>0</truncated>
  <difficult>0</difficult>
  <bndbox>
   <xmin>1136</xmin>
   <ymin>424</ymin>
   <xmax>1217</xmax>
   <ymax>491</ymax>
  </bndbox>
 </object>
</annotation>
