<?xml version="1.0" ?>
<annotation>
 <folder>Cityscapes</folder>
 <filename>source_strasbourg_000001_003489_leftImg8bit.jpg</filename>
 <source>
  <database>Cityscapes</database>
  <annotation>PASCAL VOC2007</annotation>
 </source>
 <size>
  <width>2048</width>
  <height>1024</height>
  <depth>3</depth>
 </size>
 <segmented>0</segmented>
 <object>
  <name>person</name>
  <truncated>0</truncated>
  <difficult>0</difficult>
  <bndbox>
   <xmin>609</xmin>
   <ymin>332</ymin>
   <xmax>676</xmax>
   <ymax>551</ymax>
  </bndbox>
 </object>
 <object>
  <name>person</name>
  <truncated>0</truncated>
  <difficult>0</difficult>
  <bndbox>
   <xmin>509</xmin>
   <ymin>313</ymin>
   <xmax>601</xmax>
   <ymax>554</ymax>
  </bndbox>
 </object>
 <object>
  <name>car</name>
  <truncated>0</truncated>
  <difficult>0</difficult>
  <bndbox>
   <xmin>1148</xmin>
   <ymin>351</ymin>
   <xmax>1204</xmax>
   <ymax>466</ymax>
  </bndbox>
 </object>
 <object>
  <name>car</name>
  <truncated>0</truncated>
  <difficult>0</difficult>
  <bndbox>
   <xmin>817</xmin>
   <ymin>353</ymin>
   <xmax>1065</xmax>
   <ymax>535</ymax>
  </bndbox>
 </object>
</annotation>
