<?xml version="1.0" ?>
<annotation>
 <folder>Cityscapes</folder>
 <filename>source_zurich_000003_000019_leftImg8bit.jpg</filename>
 <source>
  <database>Cityscapes</database>
  <annotation>PASCAL VOC2007</annotation>
 </source>
 <size>
  <width>2048</width>
  <height>1024</height>
  <depth>3</depth>
 </size>
 <segmented>0</segmented>
 <object>
  <name>person</name>
  <truncated>0</truncated>
  <difficult>0</difficult>
  <bndbox>
   <xmin>1770</xmin>
   <ymin>395</ymin>
   <xmax>1885</xmax>
   <ymax>547</ymax>
  </bndbox>
 </object>
 <object>
  <name>car</name>
  <truncated>0</truncated>
  <difficult>0</difficult>
  <bndbox>
   <xmin>1694</xmin>
   <ymin>451</ymin>
   <xmax>1786</xmax>
   <ymax>518</ymax>
  </bndbox>
 </object>
 <object>
  <name>person</name>
  <truncated>0</truncated>
  <difficult>0</difficult>
  <bndbox>
   <xmin>1160</xmin>
   <ymin>419</ymin>
   <xmax>1208</xmax>
   <ymax>541</ymax>
  </bndbox>
 </object>
 <object>
  <name>person</name>
  <truncated>0</truncated>
  <difficult>0</difficult>
  <bndbox>
   <xmin>1137</xmin>
   <ymin>421</ymin>
   <xmax>1177</xmax>
   <ymax>539</ymax>
  </bndbox>
 </object>
 <object>
  <name>person</name>
  <truncated>0</truncated>
  <difficult>0</difficult>
  <bndbox>
   <xmin>1077</xmin>
   <ymin>421</ymin>
   <xmax>1108</xmax>
   <ymax>546</ymax>
  </bndbox>
 </object>
 <object>
  <name>person</name>
  <truncated>0</truncated>
  <difficult>0</difficult>
  <bndbox>
   <xmin>1378</xmin>
   <ymin>401</ymin>
   <xmax>1432</xmax>
   <ymax>532</ymax>
  </bndbox>
 </object>
 <object>
  <name>person</name>
  <truncated>0</truncated>
  <difficult>0</difficult>
  <bndbox>
   <xmin>1715</xmin>
   <ymin>430</ymin>
   <xmax>1756</xmax>
   <ymax>530</ymax>
  </bndbox>
 </object>
 <object>
  <name>person</name>
  <truncated>0</truncated>
  <difficult>0</difficult>
  <bndbox>
   <xmin>1657</xmin>
   <ymin>423</ymin>
   <xmax>1727</xmax>
   <ymax>533</ymax>
  </bndbox>
 </object>
 <object>
  <name>person</name>
  <truncated>0</truncated>
  <difficult>0</difficult>
  <bndbox>
   <xmin>1437</xmin>
   <ymin>400</ymin>
   <xmax>1494</xmax>
   <ymax>544</ymax>
  </bndbox>
 </object>
 <object>
  <name>person</name>
  <truncated>0</truncated>
  <difficult>0</difficult>
  <bndbox>
   <xmin>944</xmin>
   <ymin>416</ymin>
   <xmax>968</xmax>
   <ymax>518</ymax>
  </bndbox>
 </object>
 <object>
  <name>person</name>
  <truncated>0</truncated>
  <difficult>0</difficult>
  <bndbox>
   <xmin>1493</xmin>
   <ymin>404</ymin>
   <xmax>1515</xmax>
   <ymax>519</ymax>
  </bndbox>
 </object>
 <object>
  <name>person</name>
  <truncated>0</truncated>
  <difficult>0</difficult>
  <bndbox>
   <xmin>1567</xmin>
   <ymin>411</ymin>
   <xmax>1583</xmax>
   <ymax>514</ymax>
  </bndbox>
 </object>
 <object>
  <name>person</name>
  <truncated>0</truncated>
  <difficult>0</difficult>
  <bndbox>
   <xmin>1543</xmin>
   <ymin>405</ymin>
   <xmax>1575</xmax>
   <ymax>515</ymax>
  </bndbox>
 </object>
 <object>
  <name>person</name>
  <truncated>0</truncated>
  <difficult>0</difficult>
  <bndbox>
   <xmin>1603</xmin>
   <ymin>438</ymin>
   <xmax>1624</xmax>
   <ymax>515</ymax>
  </bndbox>
 </object>
 <object>
  <name>person</name>
  <truncated>0</truncated>
  <difficult>0</difficult>
  <bndbox>
   <xmin>1611</xmin>
   <ymin>408</ymin>
   <xmax>1650</xmax>
   <ymax>509</ymax>
  </bndbox>
 </object>
 <object>
  <name>person</name>
  <truncated>0</truncated>
  <difficult>0</difficult>
  <bndbox>
   <xmin>1617</xmin>
   <ymin>401</ymin>
   <xmax>1697</xmax>
   <ymax>537</ymax>
  </bndbox>
 </object>
 <object>
  <name>person</name>
  <truncated>0</truncated>
  <difficult>0</difficult>
  <bndbox>
   <xmin>1572</xmin>
   <ymin>412</ymin>
   <xmax>1611</xmax>
   <ymax>515</ymax>
  </bndbox>
 </object>
 <object>
  <name>person</name>
  <truncated>0</truncated>
  <difficult>0</difficult>
  <bndbox>
   <xmin>1524</xmin>
   <ymin>409</ymin>
   <xmax>1537</xmax>
   <ymax>504</ymax>
  </bndbox>
 </object>
 <object>
  <name>person</name>
  <truncated>0</truncated>
  <difficult>0</difficult>
  <bndbox>
   <xmin>1522</xmin>
   <ymin>419</ymin>
   <xmax>1552</xmax>
   <ymax>528</ymax>
  </bndbox>
 </object>
 <object>
  <name>person</name>
  <truncated>0</truncated>
  <difficult>0</difficult>
  <bndbox>
   <xmin>1023</xmin>
   <ymin>415</ymin>
   <xmax>1064</xmax>
   <ymax>538</ymax>
  </bndbox>
 </object>
 <object>
  <name>person</name>
  <truncated>0</truncated>
  <difficult>0</difficult>
  <bndbox>
   <xmin>1027</xmin>
   <ymin>422</ymin>
   <xmax>1086</xmax>
   <ymax>541</ymax>
  </bndbox>
 </object>
 <object>
  <name>person</name>
  <truncated>0</truncated>
  <difficult>0</difficult>
  <bndbox>
   <xmin>747</xmin>
   <ymin>420</ymin>
   <xmax>767</xmax>
   <ymax>501</ymax>
  </bndbox>
 </object>
 <object>
  <name>person</name>
  <truncated>0</truncated>
  <difficult>0</difficult>
  <bndbox>
   <xmin>764</xmin>
   <ymin>412</ymin>
   <xmax>795</xmax>
   <ymax>502</ymax>
  </bndbox>
 </object>
 <object>
  <name>person</name>
  <truncated>0</truncated>
  <difficult>0</difficult>
  <bndbox>
   <xmin>774</xmin>
   <ymin>417</ymin>
   <xmax>806</xmax>
   <ymax>504</ymax>
  </bndbox>
 </object>
 <object>
  <name>person</name>
  <truncated>0</truncated>
  <difficult>0</difficult>
  <bndbox>
   <xmin>725</xmin>
   <ymin>425</ymin>
   <xmax>764</xmax>
   <ymax>499</ymax>
  </bndbox>
 </object>
 <object>
  <name>person</name>
  <truncated>0</truncated>
  <difficult>0</difficult>
  <bndbox>
   <xmin>669</xmin>
   <ymin>410</ymin>
   <xmax>726</xmax>
   <ymax>495</ymax>
  </bndbox>
 </object>
 <object>
  <name>person</name>
  <truncated>0</truncated>
  <difficult>0</difficult>
  <bndbox>
   <xmin>845</xmin>
   <ymin>409</ymin>
   <xmax>880</xmax>
   <ymax>520</ymax>
  </bndbox>
 </object>
 <object>
  <name>person</name>
  <truncated>0</truncated>
  <difficult>0</difficult>
  <bndbox>
   <xmin>868</xmin>
   <ymin>410</ymin>
   <xmax>911</xmax>
   <ymax>535</ymax>
  </bndbox>
 </object>
 <object>
  <name>car</name>
  <truncated>0</truncated>
  <difficult>0</difficult>
  <bndbox>
   <xmin>1848</xmin>
   <ymin>430</ymin>
   <xmax>1986</xmax>
   <ymax>557</ymax>
  </bndbox>
 </object>
 <object>
  <name>car</name>
  <truncated>0</truncated>
  <difficult>0</difficult>
  <bndbox>
   <xmin>1904</xmin>
   <ymin>430</ymin>
   <xmax>2043</xmax>
   <ymax>602</ymax>
  </bndbox>
 </object>
 <object>
  <name>car</name>
  <truncated>0</truncated>
  <difficult>0</difficult>
  <bndbox>
   <xmin>1422</xmin>
   <ymin>428</ymin>
   <xmax>1448</xmax>
   <ymax>469</ymax>
  </bndbox>
 </object>
 <object>
  <name>car</name>
  <truncated>0</truncated>
  <difficult>0</difficult>
  <bndbox>
   <xmin>1224</xmin>
   <ymin>414</ymin>
   <xmax>1412</xmax>
   <ymax>576</ymax>
  </bndbox>
 </object>
 <object>
  <name>train</name>
  <truncated>0</truncated>
  <difficult>0</difficult>
  <bndbox>
   <xmin>111</xmin>
   <ymin>303</ymin>
   <xmax>973</xmax>
   <ymax>505</ymax>
  </bndbox>
 </object>
</annotation>
