<?xml version="1.0" ?>
<annotation>
 <folder>Cityscapes</folder>
 <filename>source_ulm_000052_000019_leftImg8bit.jpg</filename>
 <source>
  <database>Cityscapes</database>
  <annotation>PASCAL VOC2007</annotation>
 </source>
 <size>
  <width>2048</width>
  <height>1024</height>
  <depth>3</depth>
 </size>
 <segmented>0</segmented>
 <object>
  <name>car</name>
  <truncated>0</truncated>
  <difficult>0</difficult>
  <bndbox>
   <xmin>1080</xmin>
   <ymin>415</ymin>
   <xmax>1137</xmax>
   <ymax>431</ymax>
  </bndbox>
 </object>
 <object>
  <name>person</name>
  <truncated>0</truncated>
  <difficult>0</difficult>
  <bndbox>
   <xmin>1330</xmin>
   <ymin>401</ymin>
   <xmax>1347</xmax>
   <ymax>437</ymax>
  </bndbox>
 </object>
 <object>
  <name>person</name>
  <truncated>0</truncated>
  <difficult>0</difficult>
  <bndbox>
   <xmin>1356</xmin>
   <ymin>399</ymin>
   <xmax>1375</xmax>
   <ymax>447</ymax>
  </bndbox>
 </object>
 <object>
  <name>person</name>
  <truncated>0</truncated>
  <difficult>0</difficult>
  <bndbox>
   <xmin>1389</xmin>
   <ymin>393</ymin>
   <xmax>1426</xmax>
   <ymax>502</ymax>
  </bndbox>
 </object>
 <object>
  <name>person</name>
  <truncated>0</truncated>
  <difficult>0</difficult>
  <bndbox>
   <xmin>1038</xmin>
   <ymin>417</ymin>
   <xmax>1049</xmax>
   <ymax>437</ymax>
  </bndbox>
 </object>
 <object>
  <name>car</name>
  <truncated>0</truncated>
  <difficult>0</difficult>
  <bndbox>
   <xmin>1934</xmin>
   <ymin>395</ymin>
   <xmax>2043</xmax>
   <ymax>449</ymax>
  </bndbox>
 </object>
 <object>
  <name>car</name>
  <truncated>0</truncated>
  <difficult>0</difficult>
  <bndbox>
   <xmin>1179</xmin>
   <ymin>415</ymin>
   <xmax>1223</xmax>
   <ymax>438</ymax>
  </bndbox>
 </object>
 <object>
  <name>car</name>
  <truncated>0</truncated>
  <difficult>0</difficult>
  <bndbox>
   <xmin>1167</xmin>
   <ymin>420</ymin>
   <xmax>1222</xmax>
   <ymax>461</ymax>
  </bndbox>
 </object>
 <object>
  <name>bus</name>
  <truncated>0</truncated>
  <difficult>0</difficult>
  <bndbox>
   <xmin>1032</xmin>
   <ymin>395</ymin>
   <xmax>1080</xmax>
   <ymax>439</ymax>
  </bndbox>
 </object>
</annotation>
